[
  {
    "bg_name": "White Background",
    "bg_color": "bg-c-w300",
    "treatment": "Neutral",
    "base_color": "Abyss",
    "font_color": "t-black",
    "emphasis": [
      {
        "color_name": "Azure",
        "font_color": "t-c-b300"
      },
      {
        "color_name": "Prince",
        "font_color": "t-c-p300"
      },
      {
        "color_name": "Turtle",
        "font_color": "t-c-t300"
      }
    ],
    "error": [
      {
        "heading":"Error",
        "color_name": "Coral",
        "font_color": "t-c-r300"
      }
    ]
  },

  {
    "bg_name": "Off-White Background",
    "bg_color": "bg-c-g100",
    "treatment": "Neutral",
    "base_color": "Abyss",
    "font_color": "t-black",
    "emphasis": [
      {
        "color_name": "Azure",
        "font_color": "t-c-b300"
      },
      {
        "color_name": "Prince",
        "font_color": "t-c-p300"
      },
      {
        "color_name": "Turtle",
        "font_color": "t-c-t300"
      }
    ],
    "error": [
      {
        "heading":"Error",
        "color_name": "Coral",
        "font_color": "t-c-r300"
      }
    ]
  },

  {
    "bg_name": "Blue Background",
    "bg_color": "bg-c-b300",
    "treatment": "Neutral",
    "base_color": "Abyss",
    "font_color": "t-c-w100",
    "emphasis": [
      {
        "color_name": "White",
        "font_color": "t-c-w100"
      }
    ],
    "error": [
      {
        "heading":"Do not use this background for error text",
        "color_name": null,
        "font_color": "t-c-w100"
      }
    ]
  },

  {
    "bg_name": "Black Background",
    "bg_color": "bg-black",
    "treatment": "Neutral",
    "base_color": "Abyss",
    "font_color": "t-c-w100",
    "emphasis": [
      {
        "color_name": "Azure",
        "font_color": "t-c-b300"
      },
      {
        "color_name": "Prince",
        "font_color": "t-c-p300"
      },
      {
        "color_name": "Turtle",
        "font_color": "t-c-t300"
      }
    ],
    "error": [
      {
        "heading":"Error",
        "color_name": "Coral",
        "font_color": "t-c-r300"
      }
    ]
  }
]
